secbench/picoscope/__init__.py
secbench/picoscope/base.py
secbench/picoscope/error.py
secbench/picoscope/helpers.py
secbench/picoscope/ps2000a.py
secbench/picoscope/ps3000a.py
secbench/picoscope/ps6000.py
secbench/picoscope/types.py
secbench/picoscope/lib/__init__.py
secbench/picoscope/lib/common.py
secbench/picoscope/lib/ps2000a.py
secbench/picoscope/lib/ps3000a.py
secbench/picoscope/lib/ps6000.py
secbench_picoscope-0.4.1.dist-info/licenses/LICENSE
secbench_picoscope-0.4.1.dist-info/METADATA
secbench_picoscope-0.4.1.dist-info/WHEEL
secbench_picoscope-0.4.1.dist-info/top_level.txt
secbench_picoscope-0.4.1.dist-info/RECORD
