Metadata-Version: 2.4
Name: secbench-picoscope
Version: 0.4.1
Summary: Drivers for Picoscope devices, compliant with secbench-api
Author-email: Secbench team <support@secbench.fr>
License: 
Project-URL: Homepage, https://doc.secbench.fr
Project-URL: Bug Reports, https://github.com/CEA-Leti/secbench/issues
Project-URL: Source, https://github.com/CEA-Leti/secbench
Classifier: Programming Language :: Python :: 3
Classifier: Programming Language :: Python :: 3 :: Only
Classifier: Programming Language :: Python :: 3.10
Classifier: Programming Language :: Python :: 3.11
Classifier: Programming Language :: Python :: 3.12
Classifier: Programming Language :: Python :: 3.13
Classifier: Topic :: Security
Classifier: Topic :: Scientific/Engineering
Classifier: Intended Audience :: Developers
Classifier: Intended Audience :: Science/Research
Classifier: License :: OSI Approved :: CEA CNRS Inria Logiciel Libre License, version 2.1 (CeCILL-2.1)
Requires-Python: >=3.9
License-File: LICENSE
Requires-Dist: secbench-api>=1.7.1
Requires-Dist: numpy>=1.18
Dynamic: license-file
